ice_latency_metrics_collector
