Metadata-Version: 1.0
Name: ice-latency-metrics-collector
Version: 0.1.0a9
Summary: ZerocIce latency metrics collector
Home-page: https://github.com/3g0r/ice-latency-metrics-collector
Author: 3g0r
Author-email: eg0r.n1k0l43v@gmail.com
License: MIT
Keywords: ice,latency,statsd,zeroc
Platform: UNKNOWN
